gameeapi/__init__.py
gameeapi/gamee_api_client.py
gameeapi/version.py
gameeapi-1.0.2.dist-info/METADATA
gameeapi-1.0.2.dist-info/WHEEL
gameeapi-1.0.2.dist-info/RECORD
