Metadata-Version: 2.3
Name: gameeapi
Version: 1.0.2
Summary: An unofficial API wrapper for gamee.com.
Project-URL: Repository, https://github.com/zrekryu/gamee-api
Project-URL: Issues, https://github.com/zrekryu/gamee-api/issues
Author-email: Zrekryu <zrekryu@gmail.com>
Keywords: gamee,gamee-api,telegram,telegrambot
Classifier: Development Status :: 5 - Production/Stable
Classifier: Intended Audience :: Developers
Classifier: License :: OSI Approved :: MIT License
Classifier: Operating System :: OS Independent
Classifier: Programming Language :: Python
Classifier: Programming Language :: Python :: 3.11
Classifier: Programming Language :: Python :: 3.12
Requires-Python: >=3.11
Requires-Dist: httpx
